{
    "name": "Core",
    "alias": "core",
    "description": "The core module for Collabmed Platform. This is required for every install.",
    "keywords": [],
    "active": 1,
    "order": 0,
    "providers": [
        "Ignite\\Core\\Providers\\CoreServiceProvider",
        "Ignite\\Core\\Providers\\ThemeServiceProvider",
        "Ignite\\Core\\Providers\\EventServiceProvider",
        "Ignite\\Core\\Providers\\SidebarServiceProvider",
        "Ignite\\Core\\Providers\\AssetServiceProvider",
        "Ignite\\Core\\Providers\\DashboardServiceProvider",
        "Ignite\\Core\\Providers\\WidgetServiceProvider",
        "Ignite\\Core\\Providers\\RouteServiceProvider",
        "Collective\\Html\\HtmlServiceProvider",
        "Laracasts\\Flash\\FlashServiceProvider",
        "FloatingPoint\\Stylist\\StylistServiceProvider",
        "Maatwebsite\\Sidebar\\SidebarServiceProvider",
        "Jenssegers\\Date\\DateServiceProvider"
    ],
    "aliases": {
        "Form": "Collective\\Html\\FormFacade",
        "Flash": "Laracasts\\Flash\\Flash",
        "Date": "Jenssegers\\Date\\Date"
    },
    "files": [
        "helpers.php",
        "composers.php"
    ],
    "version": "v1.0.0",
    "author": [
        {
            "name": "Samuel Odhiambo",
            "email": "sodhiambo@collabmed.com"
        }
    ]
}